pysmi/__init__.py
pysmi/compat.py
pysmi/compiler.py
pysmi/config.py
pysmi/debug.py
pysmi/error.py
pysmi/mibinfo.py
pysmi-1.6.0.dist-info/licenses/LICENSE.rst
pysmi-1.6.0.dist-info/METADATA
pysmi-1.6.0.dist-info/WHEEL
pysmi-1.6.0.dist-info/entry_points.txt
pysmi-1.6.0.dist-info/top_level.txt
pysmi-1.6.0.dist-info/RECORD
