Metadata-Version: 2.4
Name: pysmi
Version: 1.6.0
Summary: A pure-Python implementation of SNMP/SMI MIB parsing and conversion library.
Author-email: Ilya Etingof <etingof@gmail.com>, "LeXtudio Inc." <support@lextudio.com>
License: BSD-2-Clause
Project-URL: Repository, https://github.com/lextudio/pysmi
Classifier: Development Status :: 5 - Production/Stable
Classifier: Environment :: Console
Classifier: Intended Audience :: Developers
Classifier: Intended Audience :: Information Technology
Classifier: Intended Audience :: System Administrators
Classifier: Intended Audience :: Telecommunications Industry
Classifier: Natural Language :: English
Classifier: Operating System :: OS Independent
Classifier: Topic :: Communications
Classifier: Topic :: Software Development :: Libraries :: Python Modules
Requires-Python: >=3.9
License-File: LICENSE.rst
Requires-Dist: ply>=3.11
Requires-Dist: Jinja2>=3.1.3
Requires-Dist: requests>=2.26.0
Provides-Extra: dev
Requires-Dist: pysnmp>=7.1.16; extra == "dev"
Requires-Dist: pytest>=6.2.5; extra == "dev"
Requires-Dist: pytest-cov>=3.0.0; extra == "dev"
Requires-Dist: black==22.3.0; extra == "dev"
Requires-Dist: pre-commit==2.21.0; extra == "dev"
Requires-Dist: isort>=5.10.1; extra == "dev"
Requires-Dist: sphinx-sitemap-lextudio>=2.5.2; extra == "dev"
Requires-Dist: sphinx>=7.0.0; extra == "dev"
Requires-Dist: furo>=2023.1.1; extra == "dev"
Requires-Dist: sphinx-copybutton>=0.5.2; extra == "dev"
Requires-Dist: doc8>=1.1.1; extra == "dev"
Requires-Dist: sphinx-notfound-page>=1.0.0; extra == "dev"
Requires-Dist: flake8>=5.0.4; extra == "dev"
Requires-Dist: flake8-import-order>=0.18.2; extra == "dev"
Requires-Dist: flake8-docstrings>=1.7.0; extra == "dev"
Requires-Dist: flake8-rst-docstrings>=0.3.0; extra == "dev"
Requires-Dist: pep8-naming>=0.14.1; extra == "dev"
Requires-Dist: bump2version>=1.0.1; extra == "dev"
Dynamic: license-file
